sealman_edge_api/__init__.py
sealman_edge_api/api.py
sealman_edge_api/constants.py
sealman_edge_api/exceptions.py
sealman_edge_api/helper.py
sealman_edge_api/message_handler.py
sealman_edge_api/method_handler.py
sealman_edge_api/method_runner.py
sealman_edge_api/node_observer.py
sealman_edge_api/version.json
sealman_edge_api/schemas/method_req.json
sealman_edge_api/schemas/response.json
sealman_edge_api-0.8.0.dist-info/LICENSE
sealman_edge_api-0.8.0.dist-info/METADATA
sealman_edge_api-0.8.0.dist-info/WHEEL
sealman_edge_api-0.8.0.dist-info/top_level.txt
sealman_edge_api-0.8.0.dist-info/RECORD
