Metadata-Version: 2.2
Name: sealman-edge-api
Version: 0.8.0
Summary: SEALMAN Edge lib for easy communication within the SEALMAN Open Source Ecosystem
Home-page: https://github.com/Wolf-Pack-Foundation/sealman-lib-edge-api
Author: Thomas Baur
Author-email: thomas.baur@gea.com
Classifier: Programming Language :: Python :: 3
Classifier: License :: OSI Approved :: MIT License
Classifier: Operating System :: OS Independent
Requires-Python: >=3.12
License-File: LICENSE
Requires-Dist: paho-mqtt==1.6.1
Requires-Dist: jsonschema>=4.21.1
Dynamic: author
Dynamic: author-email
Dynamic: classifier
Dynamic: description
Dynamic: description-content-type
Dynamic: home-page
Dynamic: requires-dist
Dynamic: requires-python
Dynamic: summary
